owens_cool_python_package/__init__.py
owens_cool_python_package/setup.py
owens_cool_python_package-0.1.1.dist-info/WHEEL
owens_cool_python_package-0.1.1.dist-info/METADATA
owens_cool_python_package-0.1.1.dist-info/RECORD
